setup.py
wheelock/__init__.py
wheelock/__main__.py
wheelock.egg-info/PKG-INFO
wheelock.egg-info/SOURCES.txt
wheelock.egg-info/dependency_links.txt
wheelock.egg-info/entry_points.txt
wheelock.egg-info/top_level.txt