Metadata-Version: 1.0
Name: wheelock
Version: 0.0.1
Summary: wheelock
Home-page: https://github.com/kkroening/wheelock
Author: Karl Kroening
Author-email: karlk@kralnet.us
License: UNKNOWN
Platform: UNKNOWN
